autobean_format/__init__.py
autobean_format/formatter.py
autobean_format/formatters/__init__.py
autobean_format/formatters/balance.py
autobean_format/formatters/base.py
autobean_format/formatters/cost.py
autobean_format/formatters/file.py
autobean_format/formatters/number.py
autobean_format/formatters/open.py
autobean_format/formatters/posting.py
autobean_format/formatters/price.py
autobean_format/formatters/tokens.py
autobean_format/internal/__init__.py
autobean_format/internal/alignment.py
autobean_format/internal/chrono.py
autobean_format/internal/iterating.py
autobean_format/internal/sorting.py
autobean_format/main.py
autobean_format/options_lib.py
autobean_format-0.1.7.dist-info/entry_points.txt
autobean_format-0.1.7.dist-info/WHEEL
autobean_format-0.1.7.dist-info/METADATA
autobean_format-0.1.7.dist-info/licenses/LICENSE
autobean_format-0.1.7.dist-info/RECORD
