Metadata-Version: 2.1
Name: autobean-format
Version: 0.1.7
Summary: Yet another formatter for beancount
License: MIT
Author-email: SEIAROTg <seiarotg@gmail.com>
Requires-Python: >=3.10
Requires-Dist: autobean-refactor>=0.2.3
Requires-Dist: typing-extensions>=4.4.0
